python_odt_template/__about__.py
python_odt_template/__init__.py
python_odt_template/django.py
python_odt_template/filters.py
python_odt_template/jinja.py
python_odt_template/libreoffice.py
python_odt_template/markdown_map.py
python_odt_template/py.typed
python_odt_template/renderer.py
python_odt_template/template.py
python_odt_template/unoserver.py
python_odt_template-0.5.0.dist-info/METADATA
python_odt_template-0.5.0.dist-info/WHEEL
python_odt_template-0.5.0.dist-info/licenses/LICENSE.txt
python_odt_template-0.5.0.dist-info/RECORD
