Metadata-Version: 2.3
Name: python-odt-template
Version: 0.5.0
Project-URL: Documentation, https://github.com/Tobi-De/python-odt-template#readme
Project-URL: Issues, https://github.com/Tobi-De/python-odt-template/issues
Project-URL: Source, https://github.com/Tobi-De/python-odt-template
Author-email: Tobi DEGNON <tobidegnon@proton.me>
License-Expression: MIT
License-File: LICENSE.txt
Keywords: django,jinja2,libreoffice,odt,open-document-text
Classifier: Development Status :: 4 - Beta
Classifier: Programming Language :: Python
Classifier: Programming Language :: Python :: 3 :: Only
Classifier: Programming Language :: Python :: 3.8
Classifier: Programming Language :: Python :: 3.9
Classifier: Programming Language :: Python :: 3.10
Classifier: Programming Language :: Python :: 3.11
Classifier: Programming Language :: Python :: 3.12
Classifier: Programming Language :: Python :: Implementation :: CPython
Classifier: Programming Language :: Python :: Implementation :: PyPy
Requires-Python: >=3.8
Requires-Dist: defusedxml
Provides-Extra: django
Requires-Dist: django>=3; extra == 'django'
Provides-Extra: jinja
Requires-Dist: jinja2; extra == 'jinja'
Provides-Extra: md
Requires-Dist: markdown2; extra == 'md'
Provides-Extra: standard
Requires-Dist: jinja2; extra == 'standard'
Requires-Dist: markdown2; extra == 'standard'
Requires-Dist: unoserver; extra == 'standard'
Provides-Extra: uno
Requires-Dist: unoserver; extra == 'uno'
